<annotation>
	<folder>images</folder>
	<filename>1581211145.076939.jpg</filename>
	<path>C:\Users\Masfiq\Documents\Thesis\Ship human counting\labeling\images\1581211145.076939.jpg</path>
	<source>
		<database>Unknown</database>
	</source>
	<size>
		<width>1920</width>
		<height>1080</height>
		<depth>3</depth>
	</size>
	<segmented>0</segmented>
	<object>
		<name>person</name>
		<pose>Unspecified</pose>
		<truncated>0</truncated>
		<difficult>0</difficult>
		<bndbox>
			<xmin>963</xmin>
			<ymin>154</ymin>
			<xmax>1303</xmax>
			<ymax>664</ymax>
		</bndbox>
	</object>
	<object>
		<name>person</name>
		<pose>Unspecified</pose>
		<truncated>0</truncated>
		<difficult>0</difficult>
		<bndbox>
			<xmin>375</xmin>
			<ymin>178</ymin>
			<xmax>667</xmax>
			<ymax>582</ymax>
		</bndbox>
	</object>
	<object>
		<name>person</name>
		<pose>Unspecified</pose>
		<truncated>1</truncated>
		<difficult>0</difficult>
		<bndbox>
			<xmin>476</xmin>
			<ymin>1</ymin>
			<xmax>723</xmax>
			<ymax>281</ymax>
		</bndbox>
	</object>
	<object>
		<name>person</name>
		<pose>Unspecified</pose>
		<truncated>0</truncated>
		<difficult>0</difficult>
		<bndbox>
			<xmin>215</xmin>
			<ymin>94</ymin>
			<xmax>508</xmax>
			<ymax>448</ymax>
		</bndbox>
	</object>
</annotation>
