<annotation>
	<folder>images</folder>
	<filename>1581211138.323999.jpg</filename>
	<path>C:\Users\Masfiq\Documents\Thesis\Ship human counting\labeling\images\1581211138.323999.jpg</path>
	<source>
		<database>Unknown</database>
	</source>
	<size>
		<width>1920</width>
		<height>1080</height>
		<depth>3</depth>
	</size>
	<segmented>0</segmented>
	<object>
		<name>person</name>
		<pose>Unspecified</pose>
		<truncated>0</truncated>
		<difficult>0</difficult>
		<bndbox>
			<xmin>981</xmin>
			<ymin>355</ymin>
			<xmax>1304</xmax>
			<ymax>757</ymax>
		</bndbox>
	</object>
	<object>
		<name>person</name>
		<pose>Unspecified</pose>
		<truncated>0</truncated>
		<difficult>0</difficult>
		<bndbox>
			<xmin>530</xmin>
			<ymin>143</ymin>
			<xmax>829</xmax>
			<ymax>539</ymax>
		</bndbox>
	</object>
	<object>
		<name>person</name>
		<pose>Unspecified</pose>
		<truncated>0</truncated>
		<difficult>0</difficult>
		<bndbox>
			<xmin>250</xmin>
			<ymin>19</ymin>
			<xmax>554</xmax>
			<ymax>369</ymax>
		</bndbox>
	</object>
</annotation>
