<annotation>
	<folder>dataset2</folder>
	<filename>1581211985.086194.jpg</filename>
	<path>C:\Users\Masfiq\Documents\Thesis\Ship human counting\labeling\dataset2\1581211985.086194.jpg</path>
	<source>
		<database>Unknown</database>
	</source>
	<size>
		<width>1920</width>
		<height>1080</height>
		<depth>3</depth>
	</size>
	<segmented>0</segmented>
	<object>
		<name>person</name>
		<pose>Unspecified</pose>
		<truncated>0</truncated>
		<difficult>0</difficult>
		<bndbox>
			<xmin>833</xmin>
			<ymin>300</ymin>
			<xmax>1142</xmax>
			<ymax>681</ymax>
		</bndbox>
	</object>
	<object>
		<name>person</name>
		<pose>Unspecified</pose>
		<truncated>0</truncated>
		<difficult>0</difficult>
		<bndbox>
			<xmin>617</xmin>
			<ymin>339</ymin>
			<xmax>810</xmax>
			<ymax>656</ymax>
		</bndbox>
	</object>
	<object>
		<name>person</name>
		<pose>Unspecified</pose>
		<truncated>0</truncated>
		<difficult>0</difficult>
		<bndbox>
			<xmin>486</xmin>
			<ymin>304</ymin>
			<xmax>619</xmax>
			<ymax>522</ymax>
		</bndbox>
	</object>
	<object>
		<name>person</name>
		<pose>Unspecified</pose>
		<truncated>1</truncated>
		<difficult>0</difficult>
		<bndbox>
			<xmin>913</xmin>
			<ymin>1</ymin>
			<xmax>1111</xmax>
			<ymax>254</ymax>
		</bndbox>
	</object>
</annotation>
